zoodumper.py
zoodumper-0.1.dist-info/LICENSE
zoodumper-0.1.dist-info/METADATA
zoodumper-0.1.dist-info/WHEEL
zoodumper-0.1.dist-info/entry_points.txt
zoodumper-0.1.dist-info/top_level.txt
zoodumper-0.1.dist-info/RECORD
