Metadata-Version: 2.1
Name: zoodumper
Version: 0.1
Summary: Small utility to make a dump of zookeeper tree and store it on other host
Home-page: https://github.com/Ezhvsalate/zookeeper_dump_scripts
Author: ezhvsalate
Author-email: ezhvsalate@ya.ru
License: UNKNOWN
Platform: UNKNOWN
Classifier: Programming Language :: Python :: 3
Classifier: License :: OSI Approved :: MIT License
Classifier: Operating System :: OS Independent
Requires-Python: >=3.6
Requires-Dist: Click
Requires-Dist: Kazoo
